{
  "title":"Login",
  "login":"INFORMATION",
  "name":"NAME ",
  "mobile":"MOBILE",
  "address":"ADDRESS",
  "dob":"DOB",
  "logout":"Logout",
  "selectImage":"Select Image",
  "choosePhotoText":"Choose Photo from Custom Option",
  "rateMessage":"Please rate our product with the star",
  "feedbackPlaceholderMessage":"How satisfied are you with the product...?",
  "submit":"SUBMIT",
  "favScreen":"Favorites Screen",
  "homeScreen":"Home Screen",
  "nameText":"Name ",
  "brand":"Brand ",
  "category":"Category ",
  "quantity":"Quantity ",
  "price":"Price ",
  "email":"Email",
  "password":"Password",
  "changeLanguage":"Change Language",
  "orderScreen":"Order Screen",
  "login_title":"Login",
  "signup_title": "Signup",
  "Select_Date": "Select Date",
  "signup_address":"Address",
  "signup_name":"Name ",
  "Edit": "Edit",
  "Update": "Update",
  "ChangePassword": "Change Password",
  "ForgotYourPass": "Forgot Your Password?",
  "ResetYourPass": "Set Your Password?",
  "ForgotPassDesCription": "Enter your email below to receive password reset instructions.",
  "ResetPassDesCription": "Enter your new password below to reset it.",
  "Recover": "RECOVER",
  "Reset": "RESET",
  "Back": "BACK",
  "SendNotifications": "Send Notifications",
  "EditProfile": "Edit Profile",
  "MyFavorites": "My Favorites",
  "MyReviews": "My Reviews",
  "About": "About",
  "PriceRange": "Price Range",
  "Filters": "Filters",
  "Brands": "Brands",
  "Categories": "Categories",
  "SortBy": "Sort By",
  "NameAZ": "Name (A-Z)",
  "HighlyRated": "Highly Rated",
  "ApplyFilter": "APPLY FILTER",
  "order": "Orders",
  "orderDetails": "Order Details",
  "orderNo": "Order No"
}